client/__init__.py
client/client.py
client/client_classes.py
client/client_manager_class.py
client/client_storage_class.py
client/dialog_window_classes.py
client/main_window_class.py
client/common/__init__.py
client/common/custom_exceptions.py
client/common/decos.py
client/common/descriptors.py
client/common/metaclasses.py
client/common/utils.py
client/common/variables.py
client/logs/__init__.py
client/logs/client_log_config.py
client/ui/__init__.py
client/ui/add_contact.py
client/ui/del_contact.py
client/ui/input_name.py
client/ui/main_window.py
helens_messenger_client-0.0.1.dist-info/METADATA
helens_messenger_client-0.0.1.dist-info/WHEEL
helens_messenger_client-0.0.1.dist-info/top_level.txt
helens_messenger_client-0.0.1.dist-info/RECORD
